stdlib/__init__.py
stdlib/stdlib.py
hwl_stdlib_dp-0.1.dist-info/METADATA
hwl_stdlib_dp-0.1.dist-info/WHEEL
hwl_stdlib_dp-0.1.dist-info/top_level.txt
hwl_stdlib_dp-0.1.dist-info/RECORD
