Metadata-Version: 2.2
Name: hwl-stdlib-dp
Version: 0.1
Summary: A standard library used by me frequently. A gift from me, to me, by me.
Home-page: https://github.com/davidplajner
Author: David Plajner
Author-email: dplajner@hellmann.com
Classifier: Programming Language :: Python :: 3
Classifier: License :: OSI Approved :: MIT License
Classifier: Operating System :: OS Independent
Requires-Python: >=3.6
Dynamic: author
Dynamic: author-email
Dynamic: classifier
Dynamic: description
Dynamic: description-content-type
Dynamic: home-page
Dynamic: requires-python
Dynamic: summary
